CHANGES.rst
CONTRIBUTORS.rst
DEVELOP.rst
LICENSE.rst
MANIFEST.in
README.rst
setup.cfg
setup.py
docs/frontpage.png
docs/index.rst
docs/mobile.png
docs/screenshot.png
docs/screenshot_addons.png
docs/screenshot_login.png
docs/sidebar.png
src/plonetheme/__init__.py
src/plonetheme.tokyo.egg-info/PKG-INFO
src/plonetheme.tokyo.egg-info/SOURCES.txt
src/plonetheme.tokyo.egg-info/dependency_links.txt
src/plonetheme.tokyo.egg-info/entry_points.txt
src/plonetheme.tokyo.egg-info/namespace_packages.txt
src/plonetheme.tokyo.egg-info/not-zip-safe
src/plonetheme.tokyo.egg-info/requires.txt
src/plonetheme.tokyo.egg-info/top_level.txt
src/plonetheme/tokyo/__init__.py
src/plonetheme/tokyo/configure.zcml
src/plonetheme/tokyo/interfaces.py
src/plonetheme/tokyo/setuphandlers.py
src/plonetheme/tokyo/testing.py
src/plonetheme/tokyo/upgrades.py
src/plonetheme/tokyo/upgrades.zcml
src/plonetheme/tokyo/browser/__init__.py
src/plonetheme/tokyo/browser/configure.zcml
src/plonetheme/tokyo/browser/header.py
src/plonetheme/tokyo/browser/listings.py
src/plonetheme/tokyo/browser/main_template.py
src/plonetheme/tokyo/browser/overrides.zcml
src/plonetheme/tokyo/browser/overrides/.gitkeep
src/plonetheme/tokyo/browser/overrides/cmfplone/Products.CMFPlone.resources.browser.styles.pt
src/plonetheme/tokyo/browser/overrides/cmfplone/Products.CMFPlone.skins.plone_prefs.password_form.pt
src/plonetheme/tokyo/browser/overrides/cmfplone/Products.CMFPlone.skins.plone_prefs.prefs_main_template.pt
src/plonetheme/tokyo/browser/overrides/cmfplone/Products.CMFPlone.skins.plone_templates.recently_modified.pt
src/plonetheme/tokyo/browser/overrides/cmfplone/Products.CMFPlone.skins.plone_templates.recently_published.pt
src/plonetheme/tokyo/browser/overrides/cmfplone/Products.CMFPlone.skins.plone_templates.test_rendering.pt
src/plonetheme/tokyo/browser/overrides/cmfplone/controlpanel/Products.CMFPlone.controlpanel.browser.actions.pt
src/plonetheme/tokyo/browser/overrides/cmfplone/controlpanel/Products.CMFPlone.controlpanel.browser.controlpanel_usergroups_layout.pt
src/plonetheme/tokyo/browser/overrides/cmfplone/controlpanel/Products.CMFPlone.controlpanel.browser.emaillogin.pt
src/plonetheme/tokyo/browser/overrides/cmfplone/controlpanel/Products.CMFPlone.controlpanel.browser.filter_controlpanel.pt
