Metadata-Version: 2.1
Name: plonetheme.tokyo
Version: 1.0.0
Summary: An add-on for Plone
Home-page: https://pypi.python.org/pypi/plonetheme.tokyo
Author: Stefan Antonelli
Author-email: stefan.antonelli@operun.de
License: GPL version 2
Keywords: Python Plone Theme Tokyo
Platform: UNKNOWN
Classifier: Environment :: Web Environment
Classifier: Framework :: Plone
Classifier: Framework :: Plone :: 5.2
Classifier: Programming Language :: Python
Classifier: Programming Language :: Python :: 3.7
Classifier: Programming Language :: Python :: 3.8
Classifier: Operating System :: OS Independent
Classifier: License :: OSI Approved :: GNU General Public License v2 (GPLv2)
Provides-Extra: test
